_bo4e_cli_version.py
bo4e_cli/__init__.py
bo4e_cli/__main__.py
bo4e_cli/py.typed
bo4e_cli/types.py
bo4e_cli/commands/__init__.py
bo4e_cli/commands/autocompletion.py
bo4e_cli/commands/diff.py
bo4e_cli/commands/edit.py
bo4e_cli/commands/entry.py
bo4e_cli/commands/generate.py
bo4e_cli/commands/parser.py
bo4e_cli/commands/pull.py
bo4e_cli/commands/repo.py
bo4e_cli/diff/__init__.py
bo4e_cli/diff/__main__.py
bo4e_cli/diff/diff.py
bo4e_cli/diff/filters.py
bo4e_cli/diff/matrix.py
bo4e_cli/diff/version.py
bo4e_cli/edit/__init__.py
bo4e_cli/edit/add.py
bo4e_cli/edit/non_nullable.py
bo4e_cli/edit/update_refs.py
bo4e_cli/generate/__init__.py
bo4e_cli/generate/python/__init__.py
bo4e_cli/generate/python/entry.py
bo4e_cli/generate/python/format.py
bo4e_cli/generate/python/imports.py
bo4e_cli/generate/python/parser.py
bo4e_cli/generate/python/sql_parser.py
bo4e_cli/generate/python/custom_templates/BaseModel.jinja2
bo4e_cli/generate/python/custom_templates/Config.jinja2
bo4e_cli/generate/python/custom_templates/Enum.jinja2
bo4e_cli/generate/python/custom_templates/ManyLinks.jinja2
bo4e_cli/io/__init__.py
bo4e_cli/io/changes.py
bo4e_cli/io/cleanse.py
bo4e_cli/io/config.py
bo4e_cli/io/file.py
bo4e_cli/io/git.py
bo4e_cli/io/github.py
bo4e_cli/io/matrix.py
bo4e_cli/io/schemas.py
bo4e_cli/io/version_file.py
bo4e_cli/io/console/__init__.py
bo4e_cli/io/console/console.py
bo4e_cli/io/console/monkey.py
bo4e_cli/io/console/style.py
bo4e_cli/models/__init__.py
bo4e_cli/models/changes.py
bo4e_cli/models/config.py
bo4e_cli/models/matrix.py
bo4e_cli/models/meta.py
bo4e_cli/models/schema.py
bo4e_cli/models/sqlmodel.py
bo4e_cli/models/version.py
bo4e_cli/models/weakref.py
bo4e_cli/utils/__init__.py
bo4e_cli/utils/data_structures.py
bo4e_cli/utils/fields.py
bo4e_cli/utils/github_cli.py
bo4e_cli/utils/imports.py
bo4e_cli/utils/iterator.py
bo4e_cli/utils/strings.py
bo4e_cli-0.0.3.dist-info/METADATA
bo4e_cli-0.0.3.dist-info/WHEEL
bo4e_cli-0.0.3.dist-info/entry_points.txt
bo4e_cli-0.0.3.dist-info/RECORD
