Metadata-Version: 2.4
Name: BO4E-CLI
Version: 0.0.3
Summary: CLI for developers. It contains many useful features when working on using BO4E in your own projects.
Project-URL: Changelog, https://github.com/bo4e/BO4E-CLI/releases
Project-URL: Homepage, https://github.com/bo4e/BO4E-CLI
Author-email: Leon Haffmans <leon.haffmans@hochfrequenz.de>
License: MIT
Keywords: bo4e,cli,development,tools
Classifier: Development Status :: 4 - Beta
Classifier: Environment :: Console
Classifier: Intended Audience :: Developers
Classifier: License :: OSI Approved :: MIT License
Classifier: Operating System :: OS Independent
Classifier: Programming Language :: Python
Classifier: Programming Language :: Python :: 3 :: Only
Classifier: Programming Language :: Python :: 3.11
Classifier: Programming Language :: Python :: 3.12
Requires-Python: >=3.11
Requires-Dist: autoflake
Requires-Dist: datamodel-code-generator
Requires-Dist: httpx
Requires-Dist: more-itertools
Requires-Dist: networkx
Requires-Dist: pydantic
Requires-Dist: pygithub
Requires-Dist: sqlmodel
Requires-Dist: typer
